setup_poetry/__init__.py
setup_poetry-0.1.0.dist-info/METADATA
setup_poetry-0.1.0.dist-info/WHEEL
setup_poetry-0.1.0.dist-info/RECORD
