Metadata-Version: 2.3
Name: setup-poetry
Version: 0.1.0
Summary: 
Author: wallace-graca
Author-email: wallace.camargo@galp.com
Requires-Python: >=3.11
Classifier: Programming Language :: Python :: 3
Classifier: Programming Language :: Python :: 3.11
Classifier: Programming Language :: Python :: 3.12
Classifier: Programming Language :: Python :: 3.13
Requires-Dist: duckdb (>=1.3.2,<2.0.0)
